{
  "date": "2025-06-18",
  "timestamp": "2026-03-18T15:36:41.930707",
  "signals": [
    {
      "type": "HOLD",
      "direction": "LONG",
      "confidence": 0.5822219252586365,
      "validated": true
    }
  ],
  "actions": [
    {
      "date": "2025-06-18",
      "action": "SELL",
      "symbol": "2330",
      "shares": 10,
      "price": 1042.86,
      "pnl": 516.42,
      "pnl_pct": 5.32,
      "confidence": 0.5822,
      "regime": "BULL"
    }
  ],
  "portfolio": {
    "cash": 100937.00171238094,
    "positions_value": 0,
    "total_equity": 100937.00171238094,
    "unrealized_pnl": 0
  },
  "errors": []
}